hi_there/__init__.py
hi_there/greetings.py
share_project-1.9.16.2022.dist-info/METADATA
share_project-1.9.16.2022.dist-info/WHEEL
share_project-1.9.16.2022.dist-info/top_level.txt
share_project-1.9.16.2022.dist-info/RECORD
